trove_fm/Dockerfile
trove_fm/__init__.py
trove_fm/_version.py
trove_fm/alembic.ini
trove_fm/app/__init__.py
trove_fm/app/celery.py
trove_fm/app/celery_tasks.py
trove_fm/app/config.py
trove_fm/app/exceptions.py
trove_fm/app/main.py
trove_fm/app/api/__init__.py
trove_fm/app/api/dependencies/__init__.py
trove_fm/app/api/dependencies/auth.py
trove_fm/app/api/dependencies/database.py
trove_fm/app/api/routes/__init__.py
trove_fm/app/api/routes/company.py
trove_fm/app/api/routes/person.py
trove_fm/app/api/routes/ping.py
trove_fm/app/core/__init__.py
trove_fm/app/core/tasks.py
trove_fm/app/db/__init__.py
trove_fm/app/db/tasks.py
trove_fm/app/db/migrations/__init__.py
trove_fm/app/db/migrations/env.py
trove_fm/app/db/migrations/script.py.mako
trove_fm/app/db/migrations/versions/50e83167d58b_create_profile_tables.py
trove_fm/app/db/migrations/versions/8c3423000743_add_zip_codes.py
trove_fm/app/db/migrations/versions/__init__.py
trove_fm/app/db/migrations/versions/f989260ff4b2_create_initial_tables.py
trove_fm/app/db/repositories/__init__.py
trove_fm/app/db/repositories/base.py
trove_fm/app/db/repositories/company.py
trove_fm/app/db/repositories/person.py
trove_fm/app/db/repositories/profile.py
trove_fm/app/models/__init__.py
trove_fm/app/models/company.py
trove_fm/app/models/core.py
trove_fm/app/models/image.py
trove_fm/app/models/person.py
trove_fm/app/models/post.py
trove_fm/app/models/product.py
trove_fm/app/models/profile.py
trove_fm/app/models/service.py
trove_fm/app/models/token.py
trove_fm/app/services/__init__.py
trove_fm/app/services/authentication.py
trove_fm/app/services/email.py
trove_fm/app/services/oauth2.py
trove_fm/app/services/security.py
trove_fm/scripts/__init__.py
trove_fm/scripts/trove.py
trove_fm/scripts/trunc.py
trove_fm/tests/__init__.py
trove_fm/tests/conftest.py
trove_fm/tests/models.py
trove_fm/tests/qa.py
trove_fm/tests/test_person.py
trove_fm/tests/test_ping.py
trove_fm-0.6.1.dist-info/LICENSE
trove_fm-0.6.1.dist-info/METADATA
trove_fm-0.6.1.dist-info/WHEEL
trove_fm-0.6.1.dist-info/top_level.txt
trove_fm-0.6.1.dist-info/RECORD
